{"category": "", "original_price": "29", "description": "Deck of Photo Playing Cards", "title": "Mini Box", "price": " 9", "link": "/cities/1719-newyork-citywide/deals/614972-deck-of-photo-playing-cards", "location": "national"}
{"category": "activities", "description": "Paintball + BBQ Day Trip", "title": "Paintball: LivingSocial Original:", "price": " 69", "link": "/cities/1719-newyork-citywide/deals/575448-paintball-bbq-day-trip", "location": "NYC Citywide"}
{"category": "activities", "original_price": "41", "description": "Medieval Times: Meal + Show Ticket", "title": "Medieval Times", "price": " 27", "link": "/cities/1719-newyork-citywide/deals/627242-medieval-times-meal-show-ticket", "location": "NYC Citywide"}
{"category": "activities", "description": "NYC Boat Cruise + '80s Concert", "title": "'80s Boat Cruise: LivingSocial Ori...", "price": " 29", "link": "/cities/1719-newyork-citywide/deals/610320-nyc-boat-cruise-80s-concert", "location": "NYC Citywide"}
{"category": "", "original_price": "30", "description": "50 Issues of New York Magazine", "title": "New York Magazine", "price": " 15", "link": "/cities/1719-newyork-citywide/deals/594056-50-issues-of-new-york-magazine", "location": "NYC Citywide"}
{"category": "activities", "original_price": "50", "description": "King of the Wing II: Ticket + Beer + Wings", "title": "Tastethebest.com", "price": " 25", "link": "/cities/1719-newyork-citywide/deals/615602-king-of-the-wing-ii-ticket-beer-wings", "location": "NYC Citywide"}
{"category": "activities", "description": "\"Michael Jackson ONE\" by Cirque du Soleil", "title": "Cirque du Soleil", "price": " 107", "link": "/cities/1719-newyork-citywide/deals/627396-michael-jackson-one-by-cirque-du-soleil", "location": "NYC Midtown"}
{"category": "activities", "original_price": "87", "description": "\"Fuerza Bruta\": Extended By Demand!", "title": "Fuerza Bruta", "price": " 49", "link": "/cities/1719-newyork-citywide/deals/582190-fuerza-bruta-extended-by-demand", "location": "NYC Citywide"}
{"category": "activities", "original_price": "86", "description": "\"STOMP\": Ticket", "title": "\"STOMP\"", "price": " 57", "link": "/cities/1719-newyork-citywide/deals/627232-stomp-ticket", "location": "NYC Citywide"}
{"category": "activities", "original_price": "79", "description": "Two-Hour Photography Workshop", "title": "Sundays in New York", "price": " 39", "link": "/cities/1719-newyork-citywide/deals/609946-two-hour-photography-workshop", "location": "NYC Midtown"}
{"category": "food", "original_price": "206", "description": "Prix-Fixe Dinner for Two with a Bottle of Wine", "title": "Duo Restaurant & Lounge", "price": " 79", "link": "/cities/1719-newyork-citywide/deals/609018-prix-fixe-dinner-for-two-with-a-bottle-of-wine", "location": "NYC Midtown"}
{"category": "activities", "original_price": "140", "description": "Four Pilates Reformer or Tower Classes", "title": "Gramercy Pilates Fitness", "price": " 59", "link": "/cities/1719-newyork-citywide/deals/580670-four-pilates-reformer-or-tower-classes", "location": "NYC Downtown"}
{"category": "indulgence healthbeauty", "original_price": "120", "description": "1-Hour Massage or a Microdermabrasion Facial", "title": "Bright Spa Salon", "price": " 49", "link": "/cities/1719-newyork-citywide/deals/486572-1-hour-massage-or-a-microdermabrasion-facial", "location": "NYC Midtown"}
{"category": "activities", "original_price": "150", "description": "One Month of Unlimited Dance Classes", "title": "Piel Canela Dance Company", "price": " 30", "link": "/cities/1719-newyork-citywide/deals/512186-one-month-of-unlimited-dance-classes", "location": "NYC Midtown"}
{"category": "healthbeauty", "original_price": "85", "description": "Signature Facial with a Microdermabrasion", "title": "Freckle", "price": " 42", "link": "/cities/1719-newyork-citywide/deals/584894-signature-facial-with-a-microdermabrasion", "location": "Brooklyn"}
{"category": "food", "original_price": "60", "description": "$60 to Spend on Food and Drink", "title": "Atlantica Restaurant and L'Onda Lo...", "price": " 30", "link": "/cities/1719-newyork-citywide/deals/619014-60-to-spend-on-food-and-drink", "location": "Nassau County"}
{"category": "activities", "original_price": "51", "description": "One Hour of Pool or Ping-Pong for Two with Beer", "title": "Amsterdam Billiards", "price": " 25", "link": "/cities/1719-newyork-citywide/deals/598980-one-hour-of-pool-or-ping-pong-for-two-with-beer", "location": "NYC Downtown"}
{"category": "food", "original_price": "120", "description": "Dinner for 2 with Wine and 2 Comedy Club Tickets", "title": "Cucina di Pesce and EastVille Come...", "price": " 60", "link": "/cities/1719-newyork-citywide/deals/591012-dinner-for-2-with-wine-and-2-comedy-club-tickets", "location": "NYC Downtown"}
{"category": "activities", "original_price": "60", "description": "Two Games of Bowling & Shoe Rental for Up to Four", "title": "Play Lounge", "price": " 25", "link": "/cities/1719-newyork-citywide/deals/613912-two-games-of-bowling-shoe-rental-for-up-to-four", "location": "Queens"}
{"category": "activities", "original_price": "119", "description": "One Month of Unlimited Vinyasa Yoga Classes", "title": "Sonic Yoga", "price": " 30", "link": "/cities/1719-newyork-citywide/deals/578552-one-month-of-unlimited-vinyasa-yoga-classes", "location": "NYC Midtown"}
{"category": "healthbeauty", "original_price": "95", "description": "1-Hour Massage, Waxing Services, Mani/Pedi, & More", "title": "Lan's Spa", "price": " 47", "link": "/cities/1719-newyork-citywide/deals/602218-1-hour-massage-waxing-services-mani-pedi-more", "location": "NYC Downtown"}
{"category": "activities", "original_price": "60", "description": "Three-Course Murder Mystery Dinner", "title": "The Murder Mystery Company", "price": " 29", "link": "/cities/1719-newyork-citywide/deals/600538-three-course-murder-mystery-dinner", "location": "national"}
{"category": "activities", "original_price": "110", "description": "Paul Taylor Dance Company: Performance Ticket", "title": "Paul Taylor Dance Company", "price": " 55", "link": "/cities/1719-newyork-citywide/deals/627424-paul-taylor-dance-company-performance-ticket", "location": "NYC - Upper East Side"}
{"category": "resolutions-2013 healthbeauty", "original_price": "85", "description": "Body Wrap, 45-Minute Sauna Session, & Aromatherapy", "title": "Human@Ease", "price": " 42", "link": "/cities/1719-newyork-citywide/deals/568038-body-wrap-45-minute-sauna-session-aromatherapy", "location": "Brooklyn"}
{"category": "healthbeauty", "original_price": "295", "description": "Brazilian Keratin Treatment with Blowout", "title": "Sergio Limpopo Salon", "price": " 120", "link": "/cities/1719-newyork-citywide/deals/563704-brazilian-keratin-treatment-with-blowout", "location": "NYC Midtown"}
{"category": "food", "original_price": "102", "description": "Two Dozen Oysters and Two Martinis", "title": "Eats Restaurant & Bar", "price": " 39", "link": "/cities/1719-newyork-citywide/deals/603286-two-dozen-oysters-and-two-martinis", "location": "NYC - Upper East Side"}
{"category": "food", "original_price": "75", "description": "Lobster, Clams, and Shrimp Dinner", "title": "Knick Knacks", "price": " 37", "link": "/cities/1719-newyork-citywide/deals/611758-lobster-clams-and-shrimp-dinner", "location": "Brooklyn"}
{"category": "food", "original_price": "96", "description": "3-Course Sushi Dinner for 2 with Drinks", "title": "Asian Station", "price": " 39", "link": "/cities/1719-newyork-citywide/deals/609850-3-course-sushi-dinner-for-2-with-drinks", "location": "NYC - Upper East Side"}
{"category": "food", "original_price": "20", "description": "$20 Toward  Food and Drink or Beer & Pizza for 2", "title": "South Brooklyn Pizza", "price": " 10", "link": "/cities/1719-newyork-citywide/deals/597976-20-toward-food-and-drink-or-beer-pizza-for-2", "location": "NYC Downtown"}
{"category": "activities", "original_price": "70", "description": "VIP Wine Tasting for Two with Cheese or Chocolate", "title": "Clovis Point", "price": " 30", "link": "/cities/1719-newyork-citywide/deals/609166-vip-wine-tasting-for-two-with-cheese-or-chocolate", "location": "Nassau County"}
{"category": "activities", "original_price": "75", "description": "Ticket to See \"The Fantasticks\"", "title": "\"The Fantasticks\" on Broadway", "price": " 37", "link": "/cities/1719-newyork-citywide/deals/578158-ticket-to-see-the-fantasticks", "location": "NYC Midtown"}
{"category": "healthbeauty", "original_price": "1050", "description": "One or Three i-Lipo Treatments", "title": "Angela Azar MD", "price": " 289", "link": "/cities/1719-newyork-citywide/deals/456044-one-or-three-i-lipo-treatments", "location": "Nassau County"}
{"category": "healthbeauty", "original_price": "120", "description": "Trigger Point Acupuncture Session", "title": "Bliss Acupuncture Clinic", "price": " 39", "link": "/cities/1719-newyork-citywide/deals/616952-trigger-point-acupuncture-session", "location": "NYC - Upper West Side"}
{"category": "healthbeauty", "original_price": "514", "description": "Zoom Teeth Whitening with Dental Exam", "title": "Bridge Family Dental", "price": " 99", "link": "/cities/1719-newyork-citywide/deals/545032-zoom-teeth-whitening-with-dental-exam", "location": "Brooklyn"}
{"category": "food", "original_price": "60", "description": "Kegs & Eggs Green Breakfast: Ticket + 8 Beers", "title": "iAdventure.com", "price": " 24", "link": "/cities/1719-newyork-citywide/deals/612080-kegs-eggs-green-breakfast-ticket-8-beers", "location": "NYC Downtown"}
{"category": "", "original_price": "499", "description": "Introductory Course to Day Trading Equities", "title": "Equity Trading Capital", "price": " 99", "link": "/cities/1719-newyork-citywide/deals/620356-introductory-course-to-day-trading-equities", "location": "NYC Midtown"}
{"category": "activities", "original_price": "50", "description": "2-Hour Trampoline, Gymnastics, or High-Fall Class", "title": "Hollywood Stunts NYC", "price": " 24", "link": "/cities/1719-newyork-citywide/deals/622170-2-hour-trampoline-gymnastics-or-high-fall-class", "location": "Brooklyn"}
{"category": "healthbeauty", "original_price": "120", "description": "Brazilian Wax or Full-Body Airbrush Tans", "title": "Brows By Victoria", "price": " 39", "link": "/cities/1719-newyork-citywide/deals/567372-brazilian-wax-or-full-body-airbrush-tans", "location": "NYC - Upper East Side"}
{"category": "activities", "original_price": "100", "description": "Five Dance or Fitness Classes of Your Choice", "title": "Studio Maya", "price": " 34", "link": "/cities/1719-newyork-citywide/deals/519594-five-dance-or-fitness-classes-of-your-choice", "location": "Brooklyn"}
{"category": "healthbeauty", "original_price": "280", "description": "Keratin Treatment, Haircut, or Highlights", "title": "Extreme Color", "price": " 135", "link": "/cities/1719-newyork-citywide/deals/610548-keratin-treatment-haircut-or-highlights", "location": "NYC - Upper West Side"}
{"category": "healthbeauty", "original_price": "400", "description": "One Sclerotherapy Treatment for Spider Veins", "title": "NY Vascular Laser Center", "price": " 199", "link": "/cities/1719-newyork-citywide/deals/562526-one-sclerotherapy-treatment-for-spider-veins", "location": "NYC - Upper East Side"}
{"category": "indulgence healthbeauty nationwide", "original_price": "99", "description": "Dominate Your \u2018Do", "title": "InStyler\u00ae Rotating Hot Iron: Limit...", "price": " 69", "link": "https://www.livingsocial.com/products/us/12478-instyler-rotating-hot-iron-limited-edition-colors?preferred_city_id=1719&ref=dealxcity", "location": "shop"}
{"category": "healthbeauty", "original_price": "399", "description": "Teeth-Whitening Treatment", "title": "ModernSmile Professional Teeth Whi...", "price": " 129", "link": "/cities/1719-newyork-citywide/deals/486648-teeth-whitening-treatment", "location": "Nassau County"}
{"category": "", "original_price": "395", "description": "Basic Real Estate Sales Licensing Course", "title": "New York Real Estate Institute", "price": " 190", "link": "/cities/1719-newyork-citywide/deals/574626-basic-real-estate-sales-licensing-course", "location": "Brooklyn"}
{"category": "activities", "original_price": "80", "description": "Winter Cocktail War: One Ticket", "title": "iAdventure.com", "price": " 40", "link": "/cities/1719-newyork-citywide/deals/564580-winter-cocktail-war-one-ticket", "location": "NYC Midtown"}
{"category": "activities", "original_price": "150", "description": "Three-Hour Poker Course", "title": "School of Cards", "price": " 29", "link": "/cities/1719-newyork-citywide/deals/608122-three-hour-poker-course", "location": "NYC - Upper West Side"}
{"category": "food", "original_price": "96", "description": "3-Course Mediterranean Dinner with Wine for 2", "title": "Anatolia Mediterranean Cuisine", "price": " 48", "link": "/cities/1719-newyork-citywide/deals/607960-3-course-mediterranean-dinner-with-wine-for-2", "location": "NYC - Upper East Side"}
{"category": "activities", "original_price": "43", "description": "Laser Tag, Laser Frenzy, Maze, and Virtual Floor", "title": "Active Kidz Long Island", "price": " 20", "link": "/cities/1719-newyork-citywide/deals/573824-laser-tag-laser-frenzy-maze-and-virtual-floor", "location": "Nassau County"}
{"category": "activities", "original_price": "265", "description": "Soap Making Class or Skincare Product Class", "title": "Brooklyn Creative Studio", "price": " 85", "link": "/cities/1719-newyork-citywide/deals/583300-soap-making-class-or-skincare-product-class", "location": "Brooklyn"}
{"category": "food", "original_price": "61", "description": "Bucket of Singha Beer and $25 to Spend on Food", "title": "Jebon Noodle", "price": " 30", "link": "/cities/1719-newyork-citywide/deals/595272-bucket-of-singha-beer-and-25-to-spend-on-food", "location": "NYC Downtown"}
{"category": "", "original_price": "90", "description": "DNA Self-Discovery Kit", "title": "ConnectMyDNA", "price": " 29", "link": "/cities/1719-newyork-citywide/deals/622536-dna-self-discovery-kit", "location": "national"}
{"category": "food", "original_price": "40", "description": "$40 to Spend on Food and Drink", "title": "C\u00e1vo", "price": " 20", "link": "/cities/1719-newyork-citywide/deals/615468-40-to-spend-on-food-and-drink", "location": "Queens"}
{"category": "home", "original_price": "100", "description": "$100, $190, or $250 to Spend on Custom Framing", "title": "Skyframe & Display", "price": " 40", "link": "/cities/1719-newyork-citywide/deals/574040-100-190-or-250-to-spend-on-custom-framing", "location": "NYC Midtown"}
{"category": "", "original_price": "70", "description": "VHS to DVD Converter", "title": "Digital 007", "price": " 25", "link": "/cities/1719-newyork-citywide/deals/621840-vhs-to-dvd-converter", "location": "national"}
{"category": "activities families", "original_price": "150", "description": "Cupcake Decorating Class for a Parent and a Kid", "title": "Cake Alchemy", "price": " 50", "link": "/cities/1719-newyork-citywide/deals/598496-cupcake-decorating-class-for-a-parent-and-a-kid", "location": "NYC Downtown"}
{"category": "indulgence healthbeauty nationwide", "original_price": "99", "description": "Make Some Waves", "title": "TOPSTYLER\u00ae Curling Tool by InStyler\u00ae", "price": " 59", "link": "https://www.livingsocial.com/products/us/13184-topstyler-curling-tool-by-instyler?preferred_city_id=1719&ref=dealxcity", "location": "shop"}
{"category": "food", "original_price": "16", "description": "$16 to Spend on Coffee, Cupcakes, & Frozen Yogurt", "title": "FAO Caf\u00e9", "price": " 8", "link": "/cities/1719-newyork-citywide/deals/604042-16-to-spend-on-coffee-cupcakes-frozen-yogurt", "location": "NYC - Upper East Side"}
{"category": "food", "original_price": "39", "description": "Brunch for Two or Four", "title": "Therapy Wine Bar", "price": " 19", "link": "/cities/1719-newyork-citywide/deals/619618-brunch-for-two-or-four", "location": "Brooklyn"}
{"category": "home", "original_price": "95", "description": "House Cleaning", "title": "All Season Cleaning Services", "price": " 47", "link": "/cities/1719-newyork-citywide/deals/607124-house-cleaning", "location": "Hoboken / Jersey City"}
{"category": "activities", "original_price": "12", "description": "Metropolitan Lacrosse Classic at Citi Field", "title": "Citi Field", "price": " 6", "link": "/cities/1719-newyork-citywide/deals/630944-metropolitan-lacrosse-classic-at-citi-field", "location": "Queens"}
{"category": "families healthbeauty", "original_price": "70", "description": "Ice Cream & Spa Play Date for Two", "title": "Darlings & Divas of Amityville", "price": " 35", "link": "/cities/1719-newyork-citywide/deals/607080-ice-cream-spa-play-date-for-two", "location": "Nassau County"}
{"category": "activities families", "original_price": "99", "description": "75-Minute DJ Basics Class", "title": "Rock and Soul DJ School", "price": " 49", "link": "/cities/1719-newyork-citywide/deals/610446-75-minute-dj-basics-class", "location": "NYC Midtown"}
{"category": "activities", "description": "Cirque du Soleil \"TOTEM\": Limited Quantity Tickets", "title": "Cirque du Soleil", "price": " 76", "link": "/cities/1719-newyork-citywide/deals/618772-cirque-du-soleil-totem-limited-quantity-tickets", "location": "NYC Midtown"}
{"category": "food", "original_price": "20", "description": "$20 to Spend on Food and Drink", "title": "Kodiak's Restaurant and Bar", "price": " 10", "link": "/cities/1719-newyork-citywide/deals/613894-20-to-spend-on-food-and-drink", "location": "Nassau County"}
{"category": "food", "original_price": "40", "description": "$40 to Spend on Upscale Mexican Fare", "title": "La Condesa", "price": " 20", "link": "/cities/1719-newyork-citywide/deals/611684-40-to-spend-on-upscale-mexican-fare", "location": "NYC - Upper West Side"}
{"category": "", "original_price": "199", "description": "Two-Day Regular or Vegetarian Juice & Food Cleanse", "title": "Speedloss", "price": " 90", "link": "/cities/1719-newyork-citywide/deals/615226-two-day-regular-or-vegetarian-juice-food-cleanse", "location": "national"}
{"category": "activities", "original_price": "275", "description": "1-Month Gym Membership & Personal Training Session", "title": "David Barton Gym", "price": " 69", "link": "/cities/1719-newyork-citywide/deals/581226-1-month-gym-membership-personal-training-session", "location": "national"}
{"category": "healthbeauty", "original_price": "175", "description": "Chiropractic Consultation and Adjustment", "title": "Angrist Chiropractic & Wellness Care", "price": " 25", "link": "/cities/1719-newyork-citywide/deals/601168-chiropractic-consultation-and-adjustment", "location": "NYC - Upper West Side"}
{"category": "healthbeauty", "original_price": "255", "description": "Dental Package", "title": "Prosmiles", "price": " 75", "link": "/cities/1719-newyork-citywide/deals/591124-dental-package", "location": "Hoboken / Jersey City"}
{"category": "activities families", "original_price": "299", "description": "Two-Hour Theme Party", "title": "Dudes & Divas NYC", "price": " 149", "link": "/cities/1719-newyork-citywide/deals/615948-two-hour-theme-party", "location": "Queens"}
{"category": "activities families", "original_price": "219", "description": "Four-Week LEGO Civics & Tech Learning Program", "title": "Big Apple Education", "price": " 99", "link": "/cities/1719-newyork-citywide/deals/614468-four-week-lego-civics-tech-learning-program", "location": "NYC Midtown"}
{"category": "", "original_price": "299", "description": "Acoustic Guitar & Lessons or 2 Music/Voice Lessons", "title": "All Music's Rock-N-Roll University", "price": " 149", "link": "/cities/1719-newyork-citywide/deals/614390-acoustic-guitar-lessons-or-2-music-voice-lessons", "location": "Suffolk County, NY"}
{"category": "home", "original_price": "100", "description": "Two, Three, or Four Hours of House Cleaning", "title": "The City Cleaning Staff", "price": " 48", "link": "/cities/1719-newyork-citywide/deals/561218-two-three-or-four-hours-of-house-cleaning", "location": "NYC Midtown"}
{"category": "", "original_price": "60", "description": "3 Days of Doggie Day Care or 3 Nights of Boarding", "title": "K9CLUBHOUSE Dog Hotel", "price": " 29", "link": "/cities/1719-newyork-citywide/deals/602432-3-days-of-doggie-day-care-or-3-nights-of-boarding", "location": "Suffolk County, NY"}
{"category": "healthbeauty", "original_price": "170", "description": "Chiropractic Exam, Adjustment, & Vibration Session", "title": "NYC Back Chiropractic", "price": " 59", "link": "/cities/1719-newyork-citywide/deals/526990-chiropractic-exam-adjustment-vibration-session", "location": "NYC - Upper East Side"}
{"category": "activities", "original_price": "89", "description": "Month of Unlimited Kickboxing Classes", "title": "KO XO Kickboxing", "price": " 39", "link": "/cities/1719-newyork-citywide/deals/559516-month-of-unlimited-kickboxing-classes", "location": "Nassau County"}
{"category": "", "original_price": "1026", "description": "All-Inclusive Three-Night Stay for Two", "title": "Bel Air Collection Resort & Spa Lo...", "price": " 451", "link": "/cities/1719-newyork-citywide/deals/626068-all-inclusive-three-night-stay-for-two", "location": "Queens"}
{"category": "activities", "original_price": "120", "description": "Three-Class CrossFit Punch Card", "title": "CrossFit Transcend", "price": " 27", "link": "/cities/1719-newyork-citywide/deals/608526-three-class-crossfit-punch-card", "location": "Suffolk County, NY"}
{"category": "activities", "original_price": "40", "description": "2-Hour New York Art Tour", "title": "Merrily Kerr New York Art Tours", "price": " 20", "link": "/cities/1719-newyork-citywide/deals/594174-2-hour-new-york-art-tour", "location": "NYC Midtown"}
{"category": "", "original_price": "40", "description": "Indoor High-Definition Golf Simulator Session", "title": "St. James 1st Tee Fitness", "price": " 20", "link": "/cities/1719-newyork-citywide/deals/612160-indoor-high-definition-golf-simulator-session", "location": "Suffolk County, NY"}
{"category": "activities", "description": "Snowshoe + Fondue", "title": "Snowshoe Hike: LivingSocial Original", "price": " 89", "link": "/cities/1719-newyork-citywide/deals/597580-snowshoe-fondue", "location": "NYC Midtown"}
{"category": "activities", "original_price": "29", "description": "Performances at bergenPAC", "title": "Bergen Performing Arts Center", "price": " 14", "link": "/cities/1719-newyork-citywide/deals/612108-performances-at-bergenpac", "location": "Hoboken / Jersey City"}
{"category": "activities families", "original_price": "37", "description": "Three or Ten Open Play Sessions", "title": "Long Island City Kids", "price": " 18", "link": "/cities/1719-newyork-citywide/deals/611340-three-or-ten-open-play-sessions", "location": "Queens"}
{"category": "nationwide", "original_price": "39", "description": "5-in-1 iPad-Camera Connection Kit", "title": "TheiPadCameraKit.com", "price": " 9", "link": "/cities/1719-newyork-citywide/deals/599026-5-in-1-ipad-camera-connection-kit", "location": "national"}
{"category": "nationwide", "description": "love at first sight, quality that lasts", "title": "gucci handbags", "price": " 665", "link": "https://www.livingsocial.com/products/us/shop/guccihandbags?preferred_city_id=1719&ref=dealxcity", "location": "shop"}
{"category": "healthbeauty", "original_price": "130", "description": "Age Smart Facial or Super Facial", "title": "Grace Forever", "price": " 60", "link": "/cities/1719-newyork-citywide/deals/519402-age-smart-facial-or-super-facial", "location": "Suffolk County, NY"}
{"category": "activities families", "original_price": "110", "description": "Four 30-Minute Private Music Lessons", "title": "The Piano Studio for kids", "price": " 49", "link": "/cities/1719-newyork-citywide/deals/615480-four-30-minute-private-music-lessons", "location": "Suffolk County, NY"}
{"category": "nationwide", "original_price": "90", "description": "Austrian Crystal Bracelet", "title": "Balla Bracelets", "price": " 16", "link": "/cities/1719-newyork-citywide/deals/619034-austrian-crystal-bracelet", "location": "national"}
{"category": "activities", "original_price": "129", "description": "Art Classes at the Long Island Academy of Fine Art", "title": "Long Island Academy of Fine Art", "price": " 49", "link": "/cities/1719-newyork-citywide/deals/611618-art-classes-at-the-long-island-academy-of-fine-art", "location": "NYC Midtown"}
{"category": "food", "original_price": "20", "description": "$20 to Spend on Food and Drink at Lunch", "title": "eXo Greek Mediterranean Restaurant", "price": " 10", "link": "/cities/1719-newyork-citywide/deals/593950-20-to-spend-on-food-and-drink-at-lunch", "location": "Queens"}
{"category": "activities families", "original_price": "100", "description": "Four Beginner Fencing Lessons", "title": "North Shore Fencers Club", "price": " 39", "link": "/cities/1719-newyork-citywide/deals/587480-four-beginner-fencing-lessons", "location": "Nassau County"}
{"category": "activities", "original_price": "54", "description": "Productions at SoHo Playhouse", "title": "SoHo Playhouse", "price": " 27", "link": "/cities/1719-newyork-citywide/deals/592738-productions-at-soho-playhouse", "location": "NYC Midtown"}
{"category": "healthbeauty", "original_price": "85", "description": "Facial, Body Mask or Organic Spray Tans", "title": "Shade Bar Boutique Spa", "price": " 39", "link": "/cities/1719-newyork-citywide/deals/594052-facial-body-mask-or-organic-spray-tans", "location": "Queens"}
{"category": "nationwide", "original_price": "86", "description": "16x20 or 20x30 Photo-to-Canvas Print", "title": "MyPix2Canvas", "price": " 29", "link": "/cities/1719-newyork-citywide/deals/624098-16x20-or-20x30-photo-to-canvas-print", "location": "national"}
{"category": "", "original_price": "302", "description": "Two-Night Stay for Two in a Waterfront Room", "title": "Harrah's Resort Atlantic City", "price": " 135", "link": "/cities/1719-newyork-citywide/deals/630772-two-night-stay-for-two-in-a-waterfront-room", "location": "NYC Midtown"}
{"category": "families", "original_price": "140", "description": "One-Hour Recording Session with Customized CD", "title": "MetroSonic Recording Studio NYC", "price": " 65", "link": "/cities/1719-newyork-citywide/deals/611386-one-hour-recording-session-with-customized-cd", "location": "Brooklyn"}
{"category": "home", "original_price": "100", "description": "$100 to Spend on Framing Services", "title": "House of Art Gallery", "price": " 40", "link": "/cities/1719-newyork-citywide/deals/589050-100-to-spend-on-framing-services", "location": "Brooklyn"}
{"category": "food", "original_price": "12", "description": "$12 to Spend on Frozen Yogurt", "title": "Mojo Frozen Yogurt", "price": " 6", "link": "/cities/1719-newyork-citywide/deals/576090-12-to-spend-on-frozen-yogurt", "location": "Hoboken / Jersey City"}
{"category": "activities families", "original_price": "20", "description": "Two General Admission or Puppet Theatre Tickets", "title": "The Toy Museum of NY", "price": " 10", "link": "/cities/1719-newyork-citywide/deals/614740-two-general-admission-or-puppet-theatre-tickets", "location": "Brooklyn"}
{"category": "home", "original_price": "240", "description": "Two Hours of Moving with Three Men and a Truck", "title": "Better Move", "price": " 120", "link": "/cities/1719-newyork-citywide/deals/597884-two-hours-of-moving-with-three-men-and-a-truck", "location": "NYC Midtown"}
{"category": "nationwide", "original_price": "120", "description": "Set of Two Organic Yoga Leggings", "title": "FitwearUSA", "price": " 29", "link": "/cities/1719-newyork-citywide/deals/620554-set-of-two-organic-yoga-leggings", "location": "national"}
{"category": "nationwide", "original_price": "20", "description": "20-Page Hardcover Photo Book", "title": "MyPublisher", "price": " 5", "link": "/cities/1719-newyork-citywide/deals/624498-20-page-hardcover-photo-book", "location": "national"}
{"category": "nationwide", "original_price": "45", "description": "$45 to Spend on Custom Smartphone Cases", "title": "MyCustomCase.com", "price": " 20", "link": "/cities/1719-newyork-citywide/deals/569450-45-to-spend-on-custom-smartphone-cases", "location": "national"}
{"category": "activities families", "original_price": "25", "description": "Ticket to \"Tubby the Tuba\" Narrated by Patti Smith", "title": "The Little Orchestra Society", "price": " 15", "link": "/cities/1719-newyork-citywide/deals/583218-ticket-to-tubby-the-tuba-narrated-by-patti-smith", "location": "NYC Midtown"}
{"category": "families", "original_price": "50", "description": "Five-Week Do-Re-Mi Play Class", "title": "Do-Re-Mi Play", "price": " 25", "link": "/cities/1719-newyork-citywide/deals/588964-five-week-do-re-mi-play-class", "location": "Brooklyn"}
{"category": "home", "original_price": "100", "description": "$100 to Spend on Framing Services", "title": "FastFrame", "price": " 39", "link": "/cities/1719-newyork-citywide/deals/605446-100-to-spend-on-framing-services", "location": "Nassau County"}
{"category": "activities", "original_price": "16", "description": "Sugarloaf Crafts Festival: Two Tickets", "title": "Sugarloaf Crafts Festival", "price": " 8", "link": "/cities/1719-newyork-citywide/deals/579370-sugarloaf-crafts-festival-two-tickets", "location": "NYC Midtown"}
{"category": "home", "original_price": "900", "description": "Memory-Foam Mattress", "title": "Nature's Sleep", "price": " 339", "link": "/cities/1719-newyork-citywide/deals/596892-memory-foam-mattress", "location": "national"}
{"category": "families", "original_price": "250", "description": "On-Location Photo Shoot, DVD, & Retouched Images", "title": "Holly Hunt Photography", "price": " 99", "link": "/cities/1719-newyork-citywide/deals/577240-on-location-photo-shoot-dvd-retouched-images", "location": "Suffolk County, NY"}
{"category": "activities families", "original_price": "120", "description": "Futsal Games for Kids", "title": "New York Futsal", "price": " 59", "link": "/cities/1719-newyork-citywide/deals/620646-futsal-games-for-kids", "location": "NYC - Upper West Side"}
{"category": "families healthbeauty", "original_price": "405", "description": "Dental Exam, X-Rays, and Cleaning", "title": "Family Smile Dental", "price": " 59", "link": "/cities/1719-newyork-citywide/deals/595500-dental-exam-x-rays-and-cleaning", "location": "Queens"}
{"category": "", "original_price": "70", "description": "VHS to DVD Converter", "title": "Digital 007", "price": " 25", "link": "/cities/1719-newyork-citywide/deals/604222-vhs-to-dvd-converter", "location": "national"}
{"category": "healthbeauty", "original_price": "180", "description": "Teeth-Whitening Kit ($29) or Pens ($15)", "title": "Smiling Bright", "price": " 29", "link": "/cities/1719-newyork-citywide/deals/635232-teeth-whitening-kit-29-or-pens-15", "location": "national"}
{"category": "home", "original_price": "99", "description": "Chimney Cleaning", "title": "US Chimney", "price": " 20", "link": "/cities/1719-newyork-citywide/deals/607062-chimney-cleaning", "location": "Nassau County"}
{"category": "home", "original_price": "130", "description": "Full-House Pest Control for Up to Five Bedrooms", "title": "H2 Environmental Pest Management", "price": " 65", "link": "/cities/1719-newyork-citywide/deals/583574-full-house-pest-control-for-up-to-five-bedrooms", "location": "Queens"}
{"category": "home", "original_price": "175", "description": "Deep Cleaning of One, Two, or Three Bedrooms", "title": "Immaculate Cleaning Service", "price": " 87", "link": "/cities/1719-newyork-citywide/deals/582466-deep-cleaning-of-one-two-or-three-bedrooms", "location": "Brooklyn"}
{"category": "activities home", "original_price": "300", "description": "Two Hours of Personal Shopping or a Closet Audit", "title": "GARMNT", "price": " 150", "link": "/cities/1719-newyork-citywide/deals/554560-two-hours-of-personal-shopping-or-a-closet-audit", "location": "NYC Midtown"}
{"category": "nationwide", "original_price": "68", "description": "iPhone 5 Accessory Kit", "title": "Digital 007", "price": " 15", "link": "/cities/1719-newyork-citywide/deals/616746-iphone-5-accessory-kit", "location": "national"}
{"category": "activities families", "original_price": "200", "description": "One Month of Unlimited Dance Classes", "title": "Queens Dance Fusion", "price": " 30", "link": "/cities/1719-newyork-citywide/deals/616466-one-month-of-unlimited-dance-classes", "location": "Queens"}
{"category": "nationwide", "original_price": "130", "description": "Custom Bobblehead Doll", "title": "AllBobbleheads.com", "price": " 70", "link": "/cities/1719-newyork-citywide/deals/614286-custom-bobblehead-doll", "location": "national"}
{"category": "fun-events activities", "original_price": "140", "description": "Online Photography Class Series", "title": "Chimpsy", "price": " 34", "link": "/cities/1719-newyork-citywide/deals/613532-online-photography-class-series", "location": "national"}
{"category": "nationwide", "description": "elegant essentials for entertaining", "title": "dinner party serveware", "price": " 11", "link": "https://www.livingsocial.com/products/us/shop/dinnerpartyserveware?preferred_city_id=1719&ref=dealxcity", "location": "shop"}
{"category": "nationwide", "original_price": "70", "description": "$70 to Spend on Fine Art, Prints & More", "title": "Art.com", "price": " 35", "link": "/cities/1719-newyork-citywide/deals/609750-70-to-spend-on-fine-art-prints-more", "location": "national"}
{"category": "nationwide", "original_price": "30", "description": "$30 to Spend on T-Shirts, Hoodies, & More", "title": "BustedTees.com", "price": " 15", "link": "/cities/1719-newyork-citywide/deals/610058-30-to-spend-on-t-shirts-hoodies-more", "location": "national"}
{"category": "nationwide", "original_price": "25", "description": "iPhone and iPod Armband", "title": "LiveItNexus", "price": " 12", "link": "/cities/1719-newyork-citywide/deals/615816-iphone-and-ipod-armband", "location": "national"}
{"category": "home", "original_price": "60", "description": "Three or Twenty 30-Minute Dog or Cat Walks/Visits", "title": "Amazing Pet Care NYC", "price": " 30", "link": "/cities/1719-newyork-citywide/deals/588908-three-or-twenty-30-minute-dog-or-cat-walks-visits", "location": "NYC Midtown"}
{"category": "activities families", "original_price": "35", "description": "Percussion People: Drum Workshop + Performance", "title": "Percussion People", "price": " 17", "link": "/cities/1719-newyork-citywide/deals/624210-percussion-people-drum-workshop-performance", "location": "NYC Midtown"}
{"category": "home", "original_price": "39", "description": "Immersion Blender", "title": "Emson", "price": " 23", "link": "/cities/1719-newyork-citywide/deals/626150-immersion-blender", "location": "national"}
{"category": "families home", "original_price": "50", "description": "$50 to Spend on Wall Decals and More", "title": "Dali Decals", "price": " 20", "link": "/cities/1719-newyork-citywide/deals/615510-50-to-spend-on-wall-decals-and-more", "location": "national"}
{"category": "families", "original_price": "20", "description": "$20 to Spend on In-Store Items", "title": "Plaster Funcraft", "price": " 10", "link": "/cities/1719-newyork-citywide/deals/607394-20-to-spend-on-in-store-items", "location": "Nassau County"}
{"category": "families", "original_price": "125", "description": "Kid Power Workshop or Private-School Coaching", "title": "Kids Empowerment Academy", "price": " 39", "link": "/cities/1719-newyork-citywide/deals/596746-kid-power-workshop-or-private-school-coaching", "location": "NYC - Upper West Side"}
{"category": "", "original_price": "99", "description": "2-Carat Stud Earrings", "title": "MUI BLU", "price": " 9", "link": "/cities/1719-newyork-citywide/deals/605432-2-carat-stud-earrings", "location": "national"}
{"category": "nationwide", "original_price": "90", "description": "DNA Self-Discovery Kit", "title": "ConnectMyDNA", "price": " 29", "link": "/cities/1719-newyork-citywide/deals/617978-dna-self-discovery-kit", "location": "national"}
{"category": "exploring nationwide", "original_price": "84", "description": "Clear Sound in 11 Cool Colors", "title": "BassBuds Earbuds with Swarovski El...", "price": " 19", "link": "https://www.livingsocial.com/products/us/17075-bassbuds-earbuds?preferred_city_id=1719&ref=dealxcity", "location": "shop"}
{"category": "activities", "original_price": "37", "description": "The Hit Men & John Carfi: Ticket", "title": "Queensborough Performing Arts Center", "price": " 22", "link": "/cities/1719-newyork-citywide/deals/587540-the-hit-men-john-carfi-ticket", "location": "NYC Midtown"}
{"category": "families healthbeauty", "original_price": "41", "description": "Variety Pack of 120 Kids' Bandages", "title": "Zshoppers", "price": " 10", "link": "/cities/1719-newyork-citywide/deals/587944-variety-pack-of-120-kids-bandages", "location": "national"}
{"category": "healthbeauty", "original_price": "115", "description": "$115 to Spend on Hair Styling Tools", "title": "NuMeStyle", "price": " 15", "link": "/cities/1719-newyork-citywide/deals/592528-115-to-spend-on-hair-styling-tools", "location": "national"}
{"category": "families", "original_price": "40", "description": "$40 to Spend on Kid and Teen Clothing", "title": "Applike Couture", "price": " 20", "link": "/cities/1719-newyork-citywide/deals/615720-40-to-spend-on-kid-and-teen-clothing", "location": "NYC - Upper West Side"}
{"category": "", "original_price": "2552", "description": "All-Inclusive St. Lucia Resort", "title": "Smuggler's Cove St. Lucia", "price": " 899", "link": "/cities/1719-newyork-citywide/deals/626818-all-inclusive-st-lucia-resort", "location": "NYC - Upper West Side"}
{"category": "nationwide", "original_price": "79", "description": "Shatter-Resistant iPhone/iPad Screen Shield", "title": "ARMORTECH", "price": " 39", "link": "/cities/1719-newyork-citywide/deals/611140-shatter-resistant-iphone-ipad-screen-shield", "location": "national"}
{"category": "home", "original_price": "400", "description": "$400 Toward Window Treatments and Re-Upholstery", "title": "Prestige Home Interiors", "price": " 150", "link": "/cities/1719-newyork-citywide/deals/569956-400-toward-window-treatments-and-re-upholstery", "location": "NYC Midtown"}
{"category": "activities families", "original_price": "99", "description": "One-Month Quick-Start Program with Uniform", "title": "New Generation Karate Mixed Martia...", "price": " 29", "link": "/cities/1719-newyork-citywide/deals/536044-one-month-quick-start-program-with-uniform", "location": "Nassau County"}
{"category": "nationwide", "original_price": "44", "description": "2 Throwback iPhone Cases", "title": "Zshoppers", "price": " 10", "link": "/cities/1719-newyork-citywide/deals/587946-2-throwback-iphone-cases", "location": "national"}
{"category": "families", "original_price": "45", "description": "80 Personalized Name Labels", "title": "Tinyme", "price": " 18", "link": "/cities/1719-newyork-citywide/deals/620022-80-personalized-name-labels", "location": "national"}
{"category": "families home nationwide", "original_price": "99", "description": "Luxurious Feline Lounger", "title": "Cat Scratcher Lounge by PetFusion", "price": " 69", "link": "https://www.livingsocial.com/products/us/12256-cat-scratcher-lounge-by-petfusion?preferred_city_id=1719&ref=dealxcity", "location": "shop"}
{"category": "home", "original_price": "200", "description": "One-Hour Interior Design Consultation", "title": "Design 2 Client", "price": " 100", "link": "/cities/1719-newyork-citywide/deals/578152-one-hour-interior-design-consultation", "location": "Brooklyn"}
{"category": "home", "original_price": "39", "description": "Digital Photo Restoration Services", "title": "Creative Photo Restore", "price": " 19", "link": "/cities/1719-newyork-citywide/deals/573646-digital-photo-restoration-services", "location": "NYC Midtown"}
{"category": "families", "original_price": "40", "description": "Subscription to Phonics and Spelling Programs", "title": "ClickN KIDS", "price": " 17", "link": "/cities/1719-newyork-citywide/deals/624736-subscription-to-phonics-and-spelling-programs", "location": "national"}
{"category": "home", "original_price": "50", "description": "$50 to Spend on Locksmith Services", "title": "AM-PM Locksmith", "price": " 20", "link": "/cities/1719-newyork-citywide/deals/608502-50-to-spend-on-locksmith-services", "location": "Brooklyn"}
{"category": "nationwide", "original_price": "24", "description": "Two Spherical Ice Cube Molds", "title": "The Whiskey Ball", "price": " 12", "link": "/cities/1719-newyork-citywide/deals/613964-two-spherical-ice-cube-molds", "location": "national"}
{"category": "families", "original_price": "39", "description": "Personalized Photo Puzzle", "title": "Mini Box", "price": " 14", "link": "/cities/1719-newyork-citywide/deals/614974-personalized-photo-puzzle", "location": "national"}
{"category": "nationwide", "original_price": "50", "description": "Surrender to the Soft", "title": "Micro-Mink Sherpa Throw", "price": " 25", "link": "https://www.livingsocial.com/products/us/17651-micro-mink-sherpa-throw?preferred_city_id=1719&ref=dealxcity", "location": "shop"}
{"category": "home", "original_price": "160", "description": "Two Viscolite Dual Memory-Foam Pillows", "title": "Nature's Sleep", "price": " 79", "link": "/cities/1719-newyork-citywide/deals/616236-two-viscolite-dual-memory-foam-pillows", "location": "national"}
{"category": "nationwide", "original_price": "40", "description": "Retro Telephone Handset for Mobile Phones", "title": "Digital 007", "price": " 15", "link": "/cities/1719-newyork-citywide/deals/611500-retro-telephone-handset-for-mobile-phones", "location": "national"}
{"category": "home", "original_price": "100", "description": "Paint Sprayer", "title": "Paint Zoom", "price": " 50", "link": "/cities/1719-newyork-citywide/deals/618918-paint-sprayer", "location": "national"}
{"category": "indulgence home nationwide", "original_price": "36", "description": "Inspirational Wall Art", "title": "The Holstee Manifesto Poster", "price": " 30", "link": "https://www.livingsocial.com/products/us/12306-the-holstee-manifesto-poster?preferred_city_id=1719&ref=dealxcity", "location": "shop"}
{"category": "home", "original_price": "300", "description": "JetStream Bladeless Fan", "title": "JetStream World Class", "price": " 89", "link": "/cities/1719-newyork-citywide/deals/618240-jetstream-bladeless-fan", "location": "national"}
{"category": "nationwide", "original_price": "55", "description": "Universal Smartphone-Charging Car Mount", "title": "Digital 007", "price": " 19", "link": "/cities/1719-newyork-citywide/deals/618096-universal-smartphone-charging-car-mount", "location": "national"}
{"category": "home", "original_price": "12", "description": "1- or 2-Year Subscription", "title": "Cesar's Way", "price": " 6", "link": "/cities/1719-newyork-citywide/deals/602310-1-or-2-year-subscription", "location": "national"}
{"category": "", "original_price": "1100", "description": "All-Inclusive Four-Night Stay for Two", "title": "Viva Wyndham Azteca", "price": " 550", "link": "/cities/1719-newyork-citywide/deals/623850-all-inclusive-four-night-stay-for-two", "location": "NYC Midtown"}
{"category": "home", "original_price": "166", "description": "6-in-1 Reversible Grill", "title": "Emson", "price": " 79", "link": "/cities/1719-newyork-citywide/deals/626130-6-in-1-reversible-grill", "location": "national"}
{"category": "", "original_price": "227", "description": "Professional R\u00e9sum\u00e9, Cover Letter, & More", "title": "GuaranteedResumes.net", "price": " 84", "link": "/cities/1719-newyork-citywide/deals/616586-professional-resume-cover-letter-more", "location": "national"}
{"category": "nationwide", "original_price": "100", "description": "$100 to Spend on Sports Team Rugs", "title": "My Sports Rug", "price": " 49", "link": "/cities/1719-newyork-citywide/deals/618830-100-to-spend-on-sports-team-rugs", "location": "national"}
{"category": "nationwide", "original_price": "40", "description": "Smartphone Touch Screen Gloves", "title": "Touch Screen Gloves & Co.", "price": " 8", "link": "/cities/1719-newyork-citywide/deals/626684-smartphone-touch-screen-gloves", "location": "national"}
{"category": "home", "original_price": "60", "description": "$60 to Spend on Decorative Wall Art", "title": "Sissy Little", "price": " 30", "link": "/cities/1719-newyork-citywide/deals/619044-60-to-spend-on-decorative-wall-art", "location": "national"}
{"category": "eats-treats food nationwide", "original_price": "65", "description": "Brew Your Own Sweetened-Tea Elixir", "title": "Kombucha Brooklyn Home Brew Kit", "price": " 52", "link": "https://www.livingsocial.com/products/us/12280-kombucha-brooklyn-home-brew-kit?preferred_city_id=1719&ref=dealxcity", "location": "shop"}
{"category": "activities", "original_price": "113", "description": "BNP Paribas Showdown Tennis: Ticket", "title": "BNP Paribas Showdown at Madison Sq...", "price": " 56", "link": "/cities/1719-newyork-citywide/deals/620688-bnp-paribas-showdown-tennis-ticket", "location": "NYC Midtown"}
{"category": "indulgence home nationwide", "original_price": "59", "description": "Super-Cozy Sheets in Three Elegant Hues", "title": "4-Piece Microfiber Sheet Set", "price": " 19", "link": "https://www.livingsocial.com/products/us/17597-embroidered-microfiber-sheet-set?preferred_city_id=1719&ref=dealxcity", "location": "shop"}
{"category": "families", "original_price": "30", "description": "Hand-Held Training Walker for Infants", "title": "Meeno Babies", "price": " 15", "link": "/cities/1719-newyork-citywide/deals/618120-hand-held-training-walker-for-infants", "location": "national"}
{"category": "nationwide", "original_price": "30", "description": "$30 to Spend on Apparel", "title": "Zubaz", "price": " 15", "link": "/cities/1719-newyork-citywide/deals/611270-30-to-spend-on-apparel", "location": "national"}
{"category": "home", "original_price": "250", "description": "Custom Furniture with Consultation", "title": "ReDesign for a Dime", "price": " 99", "link": "/cities/1719-newyork-citywide/deals/602334-custom-furniture-with-consultation", "location": "Nassau County"}
{"category": "families", "original_price": "30", "description": "3-Month Subscription", "title": "PBS KIDS PLAY!", "price": " 15", "link": "/cities/1719-newyork-citywide/deals/618406-3-month-subscription", "location": "national"}
{"category": "", "original_price": "234", "description": "One-Night Stay for Two in a Deluxe Room", "title": "Bonaventure Resort & Spa", "price": " 109", "link": "/cities/1719-newyork-citywide/deals/623818-one-night-stay-for-two-in-a-deluxe-room", "location": "NYC Midtown"}
{"category": "nationwide", "original_price": "24", "description": "A\u00e7ai Natural Energy Boost Supplements", "title": "Healthy To Go", "price": " 12", "link": "/cities/1719-newyork-citywide/deals/623310-acai-natural-energy-boost-supplements", "location": "national"}
{"category": "nationwide", "original_price": "50", "description": "Crystal-Clear Conversations", "title": "Motorola H720 Bluetooth Headset", "price": " 30", "link": "https://www.livingsocial.com/products/us/17599-motorola-h720-bluetooth-headset?preferred_city_id=1719&ref=dealxcity", "location": "shop"}
{"category": "indulgence home nationwide", "original_price": "40", "description": "Energy-Efficient Lighting with Light Sensor", "title": "Yellow Solar Sunjar Lamp", "price": " 29", "link": "https://www.livingsocial.com/products/us/12248-yellow-solar-sunjar-lamp?preferred_city_id=1719&ref=dealxcity", "location": "shop"}
{"category": "eats-treats food nationwide", "original_price": "21", "description": "An appropriate time to be cheesy", "title": "Mozzarella Cheese Kit by Roaring B...", "price": " 17", "link": "https://www.livingsocial.com/products/us/13392-mozzarella-cheese-kit-by-roaring-brook-dairy?preferred_city_id=1719&ref=dealxcity", "location": "shop"}
{"category": "nationwide", "original_price": "15", "description": "The New York Times Digital Subscription", "title": "The New York Times", "price": " 1", "link": "/cities/1719-newyork-citywide/deals/599292-the-new-york-times-digital-subscription", "location": "national"}
{"category": "exploring healthbeauty home nationwide", "original_price": "98", "description": "For the Retro Jetsetter", "title": "Pan Am Layover Bag", "price": " 72", "link": "https://www.livingsocial.com/products/us/12326-pan-am-layover-bag?preferred_city_id=1719&ref=dealxcity", "location": "shop"}
{"category": "nationwide", "original_price": "20", "description": "Two Red Cup Drink Cooler Koozies", "title": "Zshoppers", "price": " 10", "link": "/cities/1719-newyork-citywide/deals/618796-two-red-cup-drink-cooler-koozies", "location": "national"}
{"category": "families home nationwide", "original_price": "129", "description": "Available in 4 Colors", "title": "pEi Pod Pet Beds with Cushion", "price": " 72", "link": "https://www.livingsocial.com/products/us/12270-ivory-pei-pod-pet-bed?preferred_city_id=1719&ref=dealxcity", "location": "shop"}
{"category": "home", "original_price": "148", "description": "20-Piece Dinnerware Set", "title": "Bambeco", "price": " 74", "link": "/cities/1719-newyork-citywide/deals/608790-20-piece-dinnerware-set", "location": "national"}
{"category": "home", "original_price": "15", "description": "One-Year Subscription", "title": "The Bark", "price": " 7", "link": "/cities/1719-newyork-citywide/deals/618200-one-year-subscription", "location": "national"}
{"category": "home", "original_price": "40", "description": "$40 to Spend Online on Wall Words", "title": "Decorative Words", "price": " 20", "link": "/cities/1719-newyork-citywide/deals/596952-40-to-spend-online-on-wall-words", "location": "national"}
{"category": "", "original_price": "895", "description": "All-Inclusive Three-Night Stay for Two", "title": "El Cozumele\u00f1o Beach Resort", "price": " 413", "link": "/cities/1719-newyork-citywide/deals/630786-all-inclusive-three-night-stay-for-two", "location": "NYC Midtown"}
{"category": "home", "original_price": "24", "description": "Pet Shampoo and Conditioner", "title": "Fresh Dog", "price": " 12", "link": "/cities/1719-newyork-citywide/deals/621498-pet-shampoo-and-conditioner", "location": "national"}
{"category": "indulgence home nationwide", "original_price": "35", "description": "Clock Powered by Water", "title": "Blue Wink Water Clock by Bedol", "price": " 24", "link": "https://www.livingsocial.com/products/us/12318-blue-wink-water-clock-by-bedol?preferred_city_id=1719&ref=dealxcity", "location": "shop"}
{"category": "nationwide", "original_price": "99", "description": "Get the Most out of Tablets on the Go", "title": "XFLEX Tablet Stand", "price": " 69 ", "link": "https://www.livingsocial.com/products/us/17435-xflex-tablet-stand?preferred_city_id=1719&ref=dealxcity", "location": "shop"}
{"category": "nationwide", "original_price": "59", "description": "For Keen Drinkers and Accommodating Hosts", "title": "Libbey Beer Glasses 25Pc Set", "price": " 45", "link": "https://www.livingsocial.com/products/us/17443-libbey-beer-glasses-25pc-set?preferred_city_id=1719&ref=dealxcity", "location": "shop"}
{"category": "exploring activities families nationwide", "original_price": "100", "description": "Injection-Molded Plastic Skateboard", "title": "Penny Skateboards", "price": " 90", "link": "https://www.livingsocial.com/products/us/12246-neon-pink-skateboard?preferred_city_id=1719&ref=dealxcity", "location": "shop"}
{"category": "nationwide", "original_price": "24", "description": "Travel in Style", "title": "Pan Am White Passport Cover", "price": " 17 ", "link": "https://www.livingsocial.com/products/us/17431-pan-am-white-passport-cover?preferred_city_id=1719&ref=dealxcity", "location": "shop"}
{"category": "nationwide", "original_price": "16", "description": "A Smart Cable Management Solution", "title": "Nice Red Goldie", "price": " 11", "link": "https://www.livingsocial.com/products/us/17445-nice-red-goldie?preferred_city_id=1719&ref=dealxcity", "location": "shop"}
{"category": "nationwide", "original_price": "14", "description": "Eliminate Tangled Cables While Charging", "title": "AViiQ USB Clip Cable for Apple Pro...", "price": " 13 ", "link": "https://www.livingsocial.com/products/us/12264-usb-charger-cable-for-apple-products?preferred_city_id=1719&ref=dealxcity", "location": "shop"}
{"category": "indulgence nationwide", "original_price": "24", "description": "A Fun Fashion Accesory", "title": "Rainbow Flag Glasses", "price": " 10", "link": "https://www.livingsocial.com/products/us/15450-rainbow-flag-glasses?preferred_city_id=1719&ref=dealxcity", "location": "shop"}
{"category": "exploring activities families nationwide", "original_price": "31", "description": "The Right Way To Play With Your Food", "title": "Jumping Hot Dog by Waliki", "price": " 18 ", "link": "https://www.livingsocial.com/products/us/14804-jumping-hot-dog-by-waliki?preferred_city_id=1719&ref=dealxcity", "location": "shop"}
{"category": "activities", "original_price": "44", "description": "St. John's Men's Basketball: Ticket", "title": "St. John's University Athletics", "price": " 29", "link": "/cities/1719-newyork-citywide/deals/610432-st-john-s-men-s-basketball-ticket", "location": "NYC Midtown"}
{"category": "", "original_price": "940", "description": "3, 4, or 5 Nights in a Luxury Suite + Massages", "title": "Hacienda Encantada Resort & Spa", "price": " 470", "link": "/cities/1719-newyork-citywide/deals/630784-3-4-or-5-nights-in-a-luxury-suite-massages", "location": "NYC Midtown"}
{"category": "families", "original_price": "40", "description": "Car Seat Installation", "title": "Precious Cargo Installers", "price": " 20", "link": "/cities/1719-newyork-citywide/deals/584328-car-seat-installation", "location": "Nassau County"}
